odoo10_addon_contract_sale-10.0.1.0.0-py2.7-nspkg.pth
odoo/addons/contract_sale/README.rst
odoo/addons/contract_sale/__init__.py
odoo/addons/contract_sale/__manifest__.py
odoo/addons/contract_sale/i18n/es.po
odoo/addons/contract_sale/security/account_analytic_account_security.xml
odoo/addons/contract_sale/security/ir.model.access.csv
odoo/addons/contract_sale/static/description/icon.png
odoo/addons/contract_sale/views/account_analytic_account_view.xml
odoo10_addon_contract_sale-10.0.1.0.0.dist-info/DESCRIPTION.rst
odoo10_addon_contract_sale-10.0.1.0.0.dist-info/METADATA
odoo10_addon_contract_sale-10.0.1.0.0.dist-info/RECORD
odoo10_addon_contract_sale-10.0.1.0.0.dist-info/WHEEL
odoo10_addon_contract_sale-10.0.1.0.0.dist-info/metadata.json
odoo10_addon_contract_sale-10.0.1.0.0.dist-info/namespace_packages.txt
odoo10_addon_contract_sale-10.0.1.0.0.dist-info/top_level.txt
